sympy_pipes/__init__.py
sympy_pipes/py.typed
sympy_pipes-0.1.0.dist-info/WHEEL
sympy_pipes-0.1.0.dist-info/METADATA
sympy_pipes-0.1.0.dist-info/RECORD
