Metadata-Version: 2.3
Name: sympy-pipes
Version: 0.1.0
Summary: A collection of Pipe definitions for working with sympy.
Author: Max Weiner
Author-email: Max Weiner <max.weiner@posteo.de>
Requires-Dist: docstring-inheritance>=2.2.2
Requires-Dist: pipe~=2.0
Requires-Dist: sympy~=1.14
Requires-Python: >=3.10
